codi_requests_oauthlib/__init__.py
codi_requests_oauthlib/auth/__init__.py
codi_requests_oauthlib-0.0.2.dist-info/WHEEL
codi_requests_oauthlib-0.0.2.dist-info/METADATA
codi_requests_oauthlib-0.0.2.dist-info/RECORD
